ceil_dlp/__init__.py
ceil_dlp/audit.py
ceil_dlp/ceil_dlp_callback.py
ceil_dlp/cli.py
ceil_dlp/config.py
ceil_dlp/middleware.py
ceil_dlp/redaction.py
ceil_dlp/whistledown.py
ceil_dlp/detectors/__init__.py
ceil_dlp/detectors/doctr_ocr.py
ceil_dlp/detectors/image_detector.py
ceil_dlp/detectors/model_matcher.py
ceil_dlp/detectors/patterns.py
ceil_dlp/detectors/pdf_detector.py
ceil_dlp/detectors/presidio_adapter.py
ceil_dlp/detectors/text_detector.py
ceil_dlp/utils/__init__.py
ceil_dlp/utils/genutils.py
ceil_dlp/utils/testutils.py
ceil_dlp-1.3.2.dist-info/licenses/LICENSE
ceil_dlp-1.3.2.dist-info/METADATA
ceil_dlp-1.3.2.dist-info/WHEEL
ceil_dlp-1.3.2.dist-info/entry_points.txt
ceil_dlp-1.3.2.dist-info/top_level.txt
ceil_dlp-1.3.2.dist-info/RECORD
