Metadata-Version: 2.4
Name: ceil-dlp
Version: 1.3.2
Summary: Data Loss Prevention plugin for LiteLLM: Block and mask PII in LLM requests with zero infrastructure overhead.
Author-email: hayder <hayder@alumni.harvard.edu>
License: MIT
Project-URL: Homepage, https://github.com/dorcha-inc/ceil-dlp
Project-URL: Documentation, https://github.com/dorcha-inc/ceil-dlp#readme
Project-URL: Repository, https://github.com/dorcha-inc/ceil-dlp
Keywords: dlp,pii,litellm,security,privacy,llm,ai,artificial intelligence,data loss prevention,data protection,data security,data privacy,ai security,ai privacy,compliance,hipaa,pci-dss,gdpr,ccpa
Classifier: Development Status :: 3 - Alpha
Classifier: Intended Audience :: Developers
Classifier: License :: OSI Approved :: MIT License
Classifier: Programming Language :: Python :: 3
Classifier: Programming Language :: Python :: 3.11
Classifier: Programming Language :: Python :: 3.12
Classifier: Programming Language :: Python :: 3.13
Requires-Python: >=3.11
License-File: LICENSE
Requires-Dist: litellm[proxy]>=1.0.0
Requires-Dist: pyyaml>=6.0
Requires-Dist: presidio-analyzer>=2.2.0
Requires-Dist: presidio-image-redactor>=0.0.50
Requires-Dist: pillow>=10.0.0
Requires-Dist: python-json-logger>=2.0.0
Requires-Dist: spacy>=3.7.0
Requires-Dist: typer>=0.9.0
Requires-Dist: pip>=24.0
Requires-Dist: pypdfium2>=4.0.0
Requires-Dist: python-doctr>=0.7.0
Requires-Dist: spacy-huggingface-pipelines>=0.0.1
Requires-Dist: transformers>=4.20.0
Requires-Dist: gliner>=0.2.0
Provides-Extra: dev
Requires-Dist: mypy>=1.0.0; extra == "dev"
Requires-Dist: pytest>=7.0.0; extra == "dev"
Requires-Dist: pytest-asyncio>=0.21.0; extra == "dev"
Requires-Dist: pytest-cov>=4.0.0; extra == "dev"
Requires-Dist: ruff>=0.1.0; extra == "dev"
Requires-Dist: types-PyYAML>=6.0.0; extra == "dev"
Requires-Dist: types-setuptools>=69.0.0; extra == "dev"
Dynamic: license-file
